LICENSE
README.md
setup.py
Raizen_ANP_Challenge2022/Raizen_ANP_Challenge2022.py
Raizen_ANP_Challenge2022.egg-info/PKG-INFO
Raizen_ANP_Challenge2022.egg-info/SOURCES.txt
Raizen_ANP_Challenge2022.egg-info/dependency_links.txt
Raizen_ANP_Challenge2022.egg-info/requires.txt
Raizen_ANP_Challenge2022.egg-info/top_level.txt