Metadata-Version: 2.1
Name: Raizen-ANP-Challenge2022
Version: 0.0.0.3
Summary: Retorna os dados corrigidos para resolver o desafio Raizen
Home-page: https://github.com/masuta16/Raizen_ANP_Challenge2022
Author: Israel Andrade
Author-email: israndade16@hotmail.com
License: MIT License
Keywords: Raizen_ANP_Challenge
Platform: UNKNOWN
License-File: LICENSE
